RTL/verification/min_case/src/vm_min_leaf.sv
module vm_min_leaf (
    input  logic a,
    input  logic b,
    output logic y
);
    assign y = a & b;
endmodule

RTL/verification/min_case/src/vm_min_stage.sv
module vm_min_stage (
    input  logic [1:0] in_bus,
    output logic       out_bit
);
    vm_min_leaf u_leaf0 (
        .a(in_bus[0]),
        .b(in_bus[1]),
        .y(out_bit)
    );
endmodule

RTL/verification/min_case/src/vm_min_top.sv
module vm_min_top (
    input  logic [1:0] in_bus,
    input  logic       sel,
    output logic       out_main,
    output logic       out_alt
);
    logic stage_y;

    vm_min_stage u_stage (
        .in_bus(in_bus),
        .out_bit(stage_y)
    );

    assign out_main = sel ? stage_y : in_bus[0];
    assign out_alt  = ~stage_y;
endmodule

RTL/verification/min_case/wave/vm_min_top_sample.vcd
$date
  2026-04-08
$end
$version
  RTLens sample wave
$end
$timescale 1ns $end
$scope module vm_min_top $end
$var wire 2 ! in_bus $end
$var wire 1 " sel $end
$var wire 1 # out_main $end
$var wire 1 $ out_alt $end
$var wire 1 % stage_y $end
$upscope $end
$enddefinitions $end
$dumpvars
b00 !
0"
0#
1$
0%
$end
#10
b01 !
1#
#20
b11 !
1%
0$
#30
1"
#40
b10 !
0%
0#
1$
#50
b11 !
1%
1#
0$
#60
0"
#70
b00 !
0%
0#
1$
#80
b01 !
1#
